{
    "BlueprintHash": [
        166,
        178,
        241,
        176,
        85,
        33,
        252,
        92,
        245,
        178,
        127,
        100,
        163,
        51,
        104,
        21,
        99,
        49,
        168,
        216,
        191,
        8,
        49,
        127,
        80,
        171,
        229,
        189,
        85,
        241,
        235,
        162,
        73,
        0,
        86,
        23,
        221,
        189,
        245,
        184,
        255,
        182,
        195,
        223,
        233,
        143,
        132,
        238,
        73,
        72,
        10,
        52,
        137,
        217,
        62,
        2,
        12,
        114,
        163,
        169,
        58,
        90,
        185,
        244
    ],
    "Comment": "",
    "Commit": "7f55e3e4e51887b151907bb98b5981d0acabbd1d",
    "Records": [
        {
            "ActionKey": 6,
            "ActionState": true,
            "CurrentTimeMS": 537,
            "LoopCounter": 7,
            "ObjectType": 1
        },
        {
            "ActionKey": 6,
            "ActionState": false,
            "CurrentTimeMS": 2455,
            "LoopCounter": 122,
            "ObjectType": 1
        },
        {
            "ActionKey": 6,
            "ActionState": true,
            "CurrentTimeMS": 3590,
            "LoopCounter": 190,
            "ObjectType": 1
        },
        {
            "ActionKey": 6,
            "ActionState": false,
            "CurrentTimeMS": 5391,
            "LoopCounter": 298,
            "ObjectType": 1
        },
        {
            "ActionKey": 3,
            "ActionState": true,
            "CurrentTimeMS": 5475,
            "LoopCounter": 303,
            "ObjectType": 1
        },
        {
            "ActionKey": 3,
            "ActionState": false,
            "CurrentTimeMS": 5942,
            "LoopCounter": 331,
            "ObjectType": 1
        },
        {
            "ActionKey": 5,
            "ActionState": true,
            "CurrentTimeMS": 5942,
            "LoopCounter": 331,
            "ObjectType": 1
        },
        {
            "ActionKey": 3,
            "ActionState": true,
            "CurrentTimeMS": 6176,
            "LoopCounter": 345,
            "ObjectType": 1
        },
        {
            "ActionKey": 5,
            "ActionState": false,
            "CurrentTimeMS": 6209,
            "LoopCounter": 347,
            "ObjectType": 1
        },
        {
            "ActionKey": 6,
            "ActionState": true,
            "CurrentTimeMS": 8846,
            "LoopCounter": 505,
            "ObjectType": 1
        },
        {
            "ActionKey": 3,
            "ActionState": false,
            "CurrentTimeMS": 8945,
            "LoopCounter": 511,
            "ObjectType": 1
        },
        {
            "ActionKey": 3,
            "ActionState": true,
            "CurrentTimeMS": 11815,
            "LoopCounter": 683,
            "ObjectType": 1
        },
        {
            "ActionKey": 6,
            "ActionState": false,
            "CurrentTimeMS": 11849,
            "LoopCounter": 685,
            "ObjectType": 1
        },
        {
            "ActionKey": 2,
            "ActionState": true,
            "CurrentTimeMS": 13099,
            "LoopCounter": 760,
            "ObjectType": 1
        },
        {
            "ActionKey": 5,
            "ActionState": true,
            "CurrentTimeMS": 13199,
            "LoopCounter": 766,
            "ObjectType": 1
        },
        {
            "ActionKey": 3,
            "ActionState": false,
            "CurrentTimeMS": 13216,
            "LoopCounter": 767,
            "ObjectType": 1
        },
        {
            "ActionKey": 2,
            "ActionState": false,
            "CurrentTimeMS": 13283,
            "LoopCounter": 771,
            "ObjectType": 1
        },
        {
            "ActionKey": 2,
            "ActionState": true,
            "CurrentTimeMS": 18305,
            "LoopCounter": 1072,
            "ObjectType": 1
        },
        {
            "ActionKey": 5,
            "ActionState": false,
            "CurrentTimeMS": 18355,
            "LoopCounter": 1075,
            "ObjectType": 1
        },
        {
            "ActionKey": 3,
            "ActionState": true,
            "CurrentTimeMS": 18388,
            "LoopCounter": 1077,
            "ObjectType": 1
        },
        {
            "ActionKey": 2,
            "ActionState": false,
            "CurrentTimeMS": 18504,
            "LoopCounter": 1084,
            "ObjectType": 1
        },
        {
            "ActionKey": 3,
            "ActionState": false,
            "CurrentTimeMS": 18504,
            "LoopCounter": 1084,
            "ObjectType": 1
        },
        {
            "ActionKey": 5,
            "ActionState": true,
            "CurrentTimeMS": 18521,
            "LoopCounter": 1085,
            "ObjectType": 1
        },
        {
            "ActionKey": 2,
            "ActionState": true,
            "CurrentTimeMS": 21007,
            "LoopCounter": 1234,
            "ObjectType": 1
        },
        {
            "ActionKey": 5,
            "ActionState": false,
            "CurrentTimeMS": 21007,
            "LoopCounter": 1234,
            "ObjectType": 1
        },
        {
            "ActionKey": 3,
            "ActionState": true,
            "CurrentTimeMS": 21074,
            "LoopCounter": 1238,
            "ObjectType": 1
        },
        {
            "ActionKey": 3,
            "ActionState": false,
            "CurrentTimeMS": 21140,
            "LoopCounter": 1242,
            "ObjectType": 1
        },
        {
            "ActionKey": 2,
            "ActionState": false,
            "CurrentTimeMS": 21190,
            "LoopCounter": 1245,
            "ObjectType": 1
        },
        {
            "ActionKey": 6,
            "ActionState": true,
            "CurrentTimeMS": 21224,
            "LoopCounter": 1247,
            "ObjectType": 1
        },
        {
            "ActionKey": 6,
            "ActionState": false,
            "CurrentTimeMS": 23693,
            "LoopCounter": 1395,
            "ObjectType": 1
        },
        {
            "ActionKey": 3,
            "ActionState": true,
            "CurrentTimeMS": 23710,
            "LoopCounter": 1396,
            "ObjectType": 1
        },
        {
            "ActionKey": 5,
            "ActionState": true,
            "CurrentTimeMS": 24160,
            "LoopCounter": 1423,
            "ObjectType": 1
        },
        {
            "ActionKey": 3,
            "ActionState": false,
            "CurrentTimeMS": 24227,
            "LoopCounter": 1427,
            "ObjectType": 1
        },
        {
            "ActionKey": 6,
            "ActionState": true,
            "CurrentTimeMS": 28781,
            "LoopCounter": 1700,
            "ObjectType": 1
        },
        {
            "ActionKey": 5,
            "ActionState": false,
            "CurrentTimeMS": 28832,
            "LoopCounter": 1703,
            "ObjectType": 1
        },
        {
            "ActionKey": 6,
            "ActionState": false,
            "CurrentTimeMS": 41511,
            "LoopCounter": 2463,
            "ObjectType": 1
        },
        {
            "ActionKey": 4,
            "ActionState": true,
            "CurrentTimeMS": 41578,
            "LoopCounter": 2467,
            "ObjectType": 1
        },
        {
            "ActionKey": 4,
            "ActionState": false,
            "CurrentTimeMS": 43112,
            "LoopCounter": 2559,
            "ObjectType": 1
        },
        {
            "ActionKey": 6,
            "ActionState": true,
            "CurrentTimeMS": 44681,
            "LoopCounter": 2653,
            "ObjectType": 1
        },
        {
            "ActionKey": 6,
            "ActionState": false,
            "CurrentTimeMS": 45415,
            "LoopCounter": 2697,
            "ObjectType": 1
        },
        {
            "ActionKey": 5,
            "ActionState": true,
            "CurrentTimeMS": 45465,
            "LoopCounter": 2700,
            "ObjectType": 1
        },
        {
            "ActionKey": 5,
            "ActionState": false,
            "CurrentTimeMS": 47835,
            "LoopCounter": 2842,
            "ObjectType": 1
        },
        {
            "ActionKey": 5,
            "ActionState": true,
            "CurrentTimeMS": 47884,
            "LoopCounter": 2845,
            "ObjectType": 1
        },
        {
            "ActionKey": 5,
            "ActionState": false,
            "CurrentTimeMS": 48368,
            "LoopCounter": 2874,
            "ObjectType": 1
        },
        {
            "ActionKey": 3,
            "ActionState": true,
            "CurrentTimeMS": 48569,
            "LoopCounter": 2886,
            "ObjectType": 1
        },
        {
            "ActionKey": 3,
            "ActionState": false,
            "CurrentTimeMS": 48819,
            "LoopCounter": 2901,
            "ObjectType": 1
        },
        {
            "ActionKey": 5,
            "ActionState": true,
            "CurrentTimeMS": 48952,
            "LoopCounter": 2909,
            "ObjectType": 1
        },
        {
            "ActionKey": 5,
            "ActionState": false,
            "CurrentTimeMS": 49769,
            "LoopCounter": 2958,
            "ObjectType": 1
        },
        {
            "ActionKey": 6,
            "ActionState": true,
            "CurrentTimeMS": 49786,
            "LoopCounter": 2959,
            "ObjectType": 1
        },
        {
            "ActionKey": 6,
            "ActionState": false,
            "CurrentTimeMS": 49986,
            "LoopCounter": 2971,
            "ObjectType": 1
        },
        {
            "ActionKey": 5,
            "ActionState": true,
            "CurrentTimeMS": 50104,
            "LoopCounter": 2978,
            "ObjectType": 1
        },
        {
            "ActionKey": 5,
            "ActionState": false,
            "CurrentTimeMS": 50436,
            "LoopCounter": 2998,
            "ObjectType": 1
        },
        {
            "ActionKey": 6,
            "ActionState": true,
            "CurrentTimeMS": 50570,
            "LoopCounter": 3006,
            "ObjectType": 1
        },
        {
            "ActionKey": 4,
            "ActionState": true,
            "CurrentTimeMS": 51087,
            "LoopCounter": 3037,
            "ObjectType": 1
        },
        {
            "ActionKey": 6,
            "ActionState": false,
            "CurrentTimeMS": 51120,
            "LoopCounter": 3039,
            "ObjectType": 1
        },
        {
            "ActionKey": 6,
            "ActionState": true,
            "CurrentTimeMS": 54808,
            "LoopCounter": 3260,
            "ObjectType": 1
        },
        {
            "ActionKey": 4,
            "ActionState": false,
            "CurrentTimeMS": 54924,
            "LoopCounter": 3267,
            "ObjectType": 1
        },
        {
            "ActionKey": 6,
            "ActionState": false,
            "CurrentTimeMS": 57310,
            "LoopCounter": 3410,
            "ObjectType": 1
        },
        {
            "ActionKey": 5,
            "ActionState": true,
            "CurrentTimeMS": 57343,
            "LoopCounter": 3412,
            "ObjectType": 1
        },
        {
            "ActionKey": 3,
            "ActionState": true,
            "CurrentTimeMS": 59329,
            "LoopCounter": 3531,
            "ObjectType": 1
        },
        {
            "ActionKey": 5,
            "ActionState": false,
            "CurrentTimeMS": 59479,
            "LoopCounter": 3540,
            "ObjectType": 1
        },
        {
            "ActionKey": 5,
            "ActionState": true,
            "CurrentTimeMS": 62866,
            "LoopCounter": 3743,
            "ObjectType": 1
        },
        {
            "ActionKey": 3,
            "ActionState": false,
            "CurrentTimeMS": 62899,
            "LoopCounter": 3745,
            "ObjectType": 1
        },
        {
            "ActionKey": 4,
            "ActionState": true,
            "CurrentTimeMS": 64784,
            "LoopCounter": 3858,
            "ObjectType": 1
        },
        {
            "ActionKey": 5,
            "ActionState": false,
            "CurrentTimeMS": 64835,
            "LoopCounter": 3861,
            "ObjectType": 1
        },
        {
            "ActionKey": 6,
            "ActionState": true,
            "CurrentTimeMS": 65135,
            "LoopCounter": 3879,
            "ObjectType": 1
        },
        {
            "ActionKey": 4,
            "ActionState": false,
            "CurrentTimeMS": 65151,
            "LoopCounter": 3880,
            "ObjectType": 1
        },
        {
            "ActionKey": 6,
            "ActionState": false,
            "CurrentTimeMS": 67237,
            "LoopCounter": 4005,
            "ObjectType": 1
        },
        {
            "ActionKey": 6,
            "ActionState": true,
            "CurrentTimeMS": 69038,
            "LoopCounter": 4113,
            "ObjectType": 1
        },
        {
            "ActionKey": 5,
            "ActionState": true,
            "CurrentTimeMS": 69339,
            "LoopCounter": 4131,
            "ObjectType": 1
        },
        {
            "ActionKey": 6,
            "ActionState": false,
            "CurrentTimeMS": 69355,
            "LoopCounter": 4132,
            "ObjectType": 1
        },
        {
            "ActionKey": 3,
            "ActionState": true,
            "CurrentTimeMS": 72826,
            "LoopCounter": 4340,
            "ObjectType": 1
        },
        {
            "ActionKey": 5,
            "ActionState": false,
            "CurrentTimeMS": 72826,
            "LoopCounter": 4340,
            "ObjectType": 1
        },
        {
            "ActionKey": 5,
            "ActionState": true,
            "CurrentTimeMS": 73193,
            "LoopCounter": 4362,
            "ObjectType": 1
        },
        {
            "ActionKey": 3,
            "ActionState": false,
            "CurrentTimeMS": 73209,
            "LoopCounter": 4363,
            "ObjectType": 1
        },
        {
            "ActionKey": 5,
            "ActionState": false,
            "CurrentTimeMS": 73760,
            "LoopCounter": 4396,
            "ObjectType": 1
        },
        {
            "ActionKey": 6,
            "ActionState": true,
            "CurrentTimeMS": 76813,
            "LoopCounter": 4579,
            "ObjectType": 1
        },
        {
            "ActionKey": 6,
            "ActionState": false,
            "CurrentTimeMS": 76896,
            "LoopCounter": 4584,
            "ObjectType": 1
        },
        {
            "ActionKey": 4,
            "ActionState": true,
            "CurrentTimeMS": 77030,
            "LoopCounter": 4592,
            "ObjectType": 1
        },
        {
            "ActionKey": 4,
            "ActionState": false,
            "CurrentTimeMS": 77263,
            "LoopCounter": 4606,
            "ObjectType": 1
        },
        {
            "ActionKey": 6,
            "ActionState": true,
            "CurrentTimeMS": 83803,
            "LoopCounter": 4998,
            "ObjectType": 1
        },
        {
            "ActionKey": 6,
            "ActionState": false,
            "CurrentTimeMS": 84604,
            "LoopCounter": 5046,
            "ObjectType": 1
        },
        {
            "ActionKey": 6,
            "ActionState": true,
            "CurrentTimeMS": 84771,
            "LoopCounter": 5056,
            "ObjectType": 1
        },
        {
            "ActionKey": 4,
            "ActionState": true,
            "CurrentTimeMS": 88541,
            "LoopCounter": 5282,
            "ObjectType": 1
        },
        {
            "ActionKey": 6,
            "ActionState": false,
            "CurrentTimeMS": 88575,
            "LoopCounter": 5284,
            "ObjectType": 1
        },
        {
            "ActionKey": 6,
            "ActionState": true,
            "CurrentTimeMS": 91444,
            "LoopCounter": 5456,
            "ObjectType": 1
        },
        {
            "ActionKey": 4,
            "ActionState": false,
            "CurrentTimeMS": 91511,
            "LoopCounter": 5460,
            "ObjectType": 1
        },
        {
            "ActionKey": 6,
            "ActionState": false,
            "CurrentTimeMS": 91628,
            "LoopCounter": 5467,
            "ObjectType": 1
        },
        {
            "ActionKey": 2,
            "ActionState": true,
            "CurrentTimeMS": 91694,
            "LoopCounter": 5471,
            "ObjectType": 1
        },
        {
            "ActionKey": 4,
            "ActionState": true,
            "CurrentTimeMS": 91812,
            "LoopCounter": 5478,
            "ObjectType": 1
        },
        {
            "ActionKey": 4,
            "ActionState": false,
            "CurrentTimeMS": 91912,
            "LoopCounter": 5484,
            "ObjectType": 1
        },
        {
            "ActionKey": 2,
            "ActionState": false,
            "CurrentTimeMS": 91961,
            "LoopCounter": 5487,
            "ObjectType": 1
        },
        {
            "ActionKey": 6,
            "ActionState": true,
            "CurrentTimeMS": 91978,
            "LoopCounter": 5488,
            "ObjectType": 1
        },
        {
            "ActionKey": 4,
            "ActionState": true,
            "CurrentTimeMS": 92279,
            "LoopCounter": 5506,
            "ObjectType": 1
        },
        {
            "ActionKey": 6,
            "ActionState": false,
            "CurrentTimeMS": 92329,
            "LoopCounter": 5509,
            "ObjectType": 1
        },
        {
            "ActionKey": 6,
            "ActionState": true,
            "CurrentTimeMS": 92612,
            "LoopCounter": 5526,
            "ObjectType": 1
        },
        {
            "ActionKey": 4,
            "ActionState": false,
            "CurrentTimeMS": 92679,
            "LoopCounter": 5530,
            "ObjectType": 1
        },
        {
            "ActionKey": 6,
            "ActionState": false,
            "CurrentTimeMS": 92846,
            "LoopCounter": 5540,
            "ObjectType": 1
        },
        {
            "ActionKey": 2,
            "ActionState": true,
            "CurrentTimeMS": 92863,
            "LoopCounter": 5541,
            "ObjectType": 1
        },
        {
            "ActionKey": 4,
            "ActionState": true,
            "CurrentTimeMS": 92912,
            "LoopCounter": 5544,
            "ObjectType": 1
        },
        {
            "ActionKey": 4,
            "ActionState": false,
            "CurrentTimeMS": 92996,
            "LoopCounter": 5549,
            "ObjectType": 1
        },
        {
            "ActionKey": 2,
            "ActionState": false,
            "CurrentTimeMS": 93046,
            "LoopCounter": 5552,
            "ObjectType": 1
        },
        {
            "ActionKey": 5,
            "ActionState": true,
            "CurrentTimeMS": 93063,
            "LoopCounter": 5553,
            "ObjectType": 1
        },
        {
            "ActionKey": 3,
            "ActionState": true,
            "CurrentTimeMS": 93262,
            "LoopCounter": 5565,
            "ObjectType": 1
        },
        {
            "ActionKey": 5,
            "ActionState": false,
            "CurrentTimeMS": 93296,
            "LoopCounter": 5567,
            "ObjectType": 1
        },
        {
            "ActionKey": 5,
            "ActionState": true,
            "CurrentTimeMS": 93463,
            "LoopCounter": 5577,
            "ObjectType": 1
        },
        {
            "ActionKey": 3,
            "ActionState": false,
            "CurrentTimeMS": 93480,
            "LoopCounter": 5578,
            "ObjectType": 1
        },
        {
            "ActionKey": 4,
            "ActionState": true,
            "CurrentTimeMS": 94398,
            "LoopCounter": 5633,
            "ObjectType": 1
        },
        {
            "ActionKey": 5,
            "ActionState": false,
            "CurrentTimeMS": 94447,
            "LoopCounter": 5636,
            "ObjectType": 1
        },
        {
            "ActionKey": 5,
            "ActionState": true,
            "CurrentTimeMS": 94781,
            "LoopCounter": 5656,
            "ObjectType": 1
        },
        {
            "ActionKey": 4,
            "ActionState": false,
            "CurrentTimeMS": 94898,
            "LoopCounter": 5663,
            "ObjectType": 1
        },
        {
            "ActionKey": 2,
            "ActionState": true,
            "CurrentTimeMS": 95065,
            "LoopCounter": 5673,
            "ObjectType": 1
        },
        {
            "ActionKey": 5,
            "ActionState": false,
            "CurrentTimeMS": 95065,
            "LoopCounter": 5673,
            "ObjectType": 1
        },
        {
            "ActionKey": 3,
            "ActionState": true,
            "CurrentTimeMS": 95181,
            "LoopCounter": 5680,
            "ObjectType": 1
        },
        {
            "ActionKey": 3,
            "ActionState": false,
            "CurrentTimeMS": 95265,
            "LoopCounter": 5685,
            "ObjectType": 1
        },
        {
            "ActionKey": 2,
            "ActionState": false,
            "CurrentTimeMS": 95298,
            "LoopCounter": 5687,
            "ObjectType": 1
        },
        {
            "ActionKey": 5,
            "ActionState": true,
            "CurrentTimeMS": 95298,
            "LoopCounter": 5687,
            "ObjectType": 1
        },
        {
            "ActionKey": 5,
            "ActionState": false,
            "CurrentTimeMS": 95516,
            "LoopCounter": 5700,
            "ObjectType": 1
        },
        {
            "ActionKey": 3,
            "ActionState": true,
            "CurrentTimeMS": 95548,
            "LoopCounter": 5702,
            "ObjectType": 1
        },
        {
            "ActionKey": 6,
            "ActionState": true,
            "CurrentTimeMS": 96199,
            "LoopCounter": 5741,
            "ObjectType": 1
        },
        {
            "ActionKey": 3,
            "ActionState": false,
            "CurrentTimeMS": 96250,
            "LoopCounter": 5744,
            "ObjectType": 1
        },
        {
            "ActionKey": 3,
            "ActionState": true,
            "CurrentTimeMS": 96800,
            "LoopCounter": 5777,
            "ObjectType": 1
        },
        {
            "ActionKey": 6,
            "ActionState": false,
            "CurrentTimeMS": 96833,
            "LoopCounter": 5779,
            "ObjectType": 1
        },
        {
            "ActionKey": 5,
            "ActionState": true,
            "CurrentTimeMS": 97951,
            "LoopCounter": 5846,
            "ObjectType": 1
        },
        {
            "ActionKey": 3,
            "ActionState": false,
            "CurrentTimeMS": 98051,
            "LoopCounter": 5852,
            "ObjectType": 1
        },
        {
            "ActionKey": 4,
            "ActionState": true,
            "CurrentTimeMS": 99002,
            "LoopCounter": 5909,
            "ObjectType": 1
        },
        {
            "ActionKey": 5,
            "ActionState": false,
            "CurrentTimeMS": 99069,
            "LoopCounter": 5913,
            "ObjectType": 1
        },
        {
            "ActionKey": 5,
            "ActionState": true,
            "CurrentTimeMS": 99302,
            "LoopCounter": 5927,
            "ObjectType": 1
        },
        {
            "ActionKey": 4,
            "ActionState": false,
            "CurrentTimeMS": 99369,
            "LoopCounter": 5931,
            "ObjectType": 1
        },
        {
            "ActionKey": 5,
            "ActionState": false,
            "CurrentTimeMS": 99902,
            "LoopCounter": 5963,
            "ObjectType": 1
        },
        {
            "ActionKey": 5,
            "ActionState": true,
            "CurrentTimeMS": 101355,
            "LoopCounter": 6050,
            "ObjectType": 1
        },
        {
            "ActionKey": 5,
            "ActionState": false,
            "CurrentTimeMS": 101788,
            "LoopCounter": 6076,
            "ObjectType": 1
        },
        {
            "ActionKey": 2,
            "ActionState": true,
            "CurrentTimeMS": 102755,
            "LoopCounter": 6134,
            "ObjectType": 1
        },
        {
            "ActionKey": 3,
            "ActionState": true,
            "CurrentTimeMS": 102856,
            "LoopCounter": 6140,
            "ObjectType": 1
        },
        {
            "ActionKey": 3,
            "ActionState": false,
            "CurrentTimeMS": 102922,
            "LoopCounter": 6144,
            "ObjectType": 1
        },
        {
            "ActionKey": 2,
            "ActionState": false,
            "CurrentTimeMS": 102972,
            "LoopCounter": 6147,
            "ObjectType": 1
        },
        {
            "ActionKey": 5,
            "ActionState": true,
            "CurrentTimeMS": 102972,
            "LoopCounter": 6147,
            "ObjectType": 1
        },
        {
            "ActionKey": 5,
            "ActionState": false,
            "CurrentTimeMS": 103206,
            "LoopCounter": 6161,
            "ObjectType": 1
        },
        {
            "ActionKey": 5,
            "ActionState": true,
            "CurrentTimeMS": 104208,
            "LoopCounter": 6221,
            "ObjectType": 1
        },
        {
            "ActionKey": 5,
            "ActionState": false,
            "CurrentTimeMS": 104340,
            "LoopCounter": 6229,
            "ObjectType": 1
        },
        {
            "ActionKey": 2,
            "ActionState": true,
            "CurrentTimeMS": 104591,
            "LoopCounter": 6244,
            "ObjectType": 1
        },
        {
            "ActionKey": 5,
            "ActionState": true,
            "CurrentTimeMS": 104725,
            "LoopCounter": 6252,
            "ObjectType": 1
        },
        {
            "ActionKey": 5,
            "ActionState": false,
            "CurrentTimeMS": 105592,
            "LoopCounter": 6304,
            "ObjectType": 1
        },
        {
            "ActionKey": 2,
            "ActionState": false,
            "CurrentTimeMS": 105625,
            "LoopCounter": 6306,
            "ObjectType": 1
        },
        {
            "ActionKey": 6,
            "ActionState": true,
            "CurrentTimeMS": 106793,
            "LoopCounter": 6376,
            "ObjectType": 1
        },
        {
            "ActionKey": 6,
            "ActionState": false,
            "CurrentTimeMS": 106977,
            "LoopCounter": 6387,
            "ObjectType": 1
        },
        {
            "ActionKey": 2,
            "ActionState": true,
            "CurrentTimeMS": 107394,
            "LoopCounter": 6412,
            "ObjectType": 1
        },
        {
            "ActionKey": 5,
            "ActionState": true,
            "CurrentTimeMS": 107461,
            "LoopCounter": 6416,
            "ObjectType": 1
        },
        {
            "ActionKey": 5,
            "ActionState": false,
            "CurrentTimeMS": 108378,
            "LoopCounter": 6471,
            "ObjectType": 1
        },
        {
            "ActionKey": 2,
            "ActionState": false,
            "CurrentTimeMS": 108412,
            "LoopCounter": 6473,
            "ObjectType": 1
        },
        {
            "ActionKey": 2,
            "ActionState": true,
            "CurrentTimeMS": 108712,
            "LoopCounter": 6491,
            "ObjectType": 1
        },
        {
            "ActionKey": 5,
            "ActionState": true,
            "CurrentTimeMS": 108811,
            "LoopCounter": 6497,
            "ObjectType": 1
        },
        {
            "ActionKey": 5,
            "ActionState": false,
            "CurrentTimeMS": 109629,
            "LoopCounter": 6546,
            "ObjectType": 1
        },
        {
            "ActionKey": 2,
            "ActionState": false,
            "CurrentTimeMS": 109696,
            "LoopCounter": 6550,
            "ObjectType": 1
        },
        {
            "ActionKey": 3,
            "ActionState": true,
            "CurrentTimeMS": 110664,
            "LoopCounter": 6608,
            "ObjectType": 1
        },
        {
            "ActionKey": 3,
            "ActionState": false,
            "CurrentTimeMS": 110764,
            "LoopCounter": 6614,
            "ObjectType": 1
        },
        {
            "ActionKey": 2,
            "ActionState": true,
            "CurrentTimeMS": 110864,
            "LoopCounter": 6620,
            "ObjectType": 1
        },
        {
            "ActionKey": 5,
            "ActionState": true,
            "CurrentTimeMS": 110930,
            "LoopCounter": 6624,
            "ObjectType": 1
        },
        {
            "ActionKey": 5,
            "ActionState": false,
            "CurrentTimeMS": 111047,
            "LoopCounter": 6631,
            "ObjectType": 1
        },
        {
            "ActionKey": 2,
            "ActionState": false,
            "CurrentTimeMS": 111148,
            "LoopCounter": 6637,
            "ObjectType": 1
        },
        {
            "ActionKey": 5,
            "ActionState": true,
            "CurrentTimeMS": 112215,
            "LoopCounter": 6701,
            "ObjectType": 1
        },
        {
            "ActionKey": 3,
            "ActionState": true,
            "CurrentTimeMS": 112432,
            "LoopCounter": 6714,
            "ObjectType": 1
        },
        {
            "ActionKey": 5,
            "ActionState": false,
            "CurrentTimeMS": 112466,
            "LoopCounter": 6716,
            "ObjectType": 1
        },
        {
            "ActionKey": 3,
            "ActionState": false,
            "CurrentTimeMS": 112615,
            "LoopCounter": 6725,
            "ObjectType": 1
        },
        {
            "ActionKey": 5,
            "ActionState": true,
            "CurrentTimeMS": 112615,
            "LoopCounter": 6725,
            "ObjectType": 1
        },
        {
            "ActionKey": 5,
            "ActionState": false,
            "CurrentTimeMS": 112949,
            "LoopCounter": 6745,
            "ObjectType": 1
        },
        {
            "ActionKey": 3,
            "ActionState": true,
            "CurrentTimeMS": 113516,
            "LoopCounter": 6779,
            "ObjectType": 1
        },
        {
            "ActionKey": 6,
            "ActionState": true,
            "CurrentTimeMS": 113683,
            "LoopCounter": 6789,
            "ObjectType": 1
        },
        {
            "ActionKey": 3,
            "ActionState": false,
            "CurrentTimeMS": 113733,
            "LoopCounter": 6792,
            "ObjectType": 1
        },
        {
            "ActionKey": 6,
            "ActionState": false,
            "CurrentTimeMS": 114234,
            "LoopCounter": 6822,
            "ObjectType": 1
        },
        {
            "ActionKey": 5,
            "ActionState": true,
            "CurrentTimeMS": 114251,
            "LoopCounter": 6823,
            "ObjectType": 1
        },
        {
            "ActionKey": 5,
            "ActionState": false,
            "CurrentTimeMS": 114418,
            "LoopCounter": 6833,
            "ObjectType": 1
        },
        {
            "ActionKey": 4,
            "ActionState": true,
            "CurrentTimeMS": 114484,
            "LoopCounter": 6837,
            "ObjectType": 1
        },
        {
            "ActionKey": 4,
            "ActionState": false,
            "CurrentTimeMS": 114768,
            "LoopCounter": 6854,
            "ObjectType": 1
        },
        {
            "ActionKey": 5,
            "ActionState": true,
            "CurrentTimeMS": 115068,
            "LoopCounter": 6872,
            "ObjectType": 1
        },
        {
            "ActionKey": 5,
            "ActionState": false,
            "CurrentTimeMS": 115469,
            "LoopCounter": 6896,
            "ObjectType": 1
        },
        {
            "ActionKey": 6,
            "ActionState": true,
            "CurrentTimeMS": 115736,
            "LoopCounter": 6912,
            "ObjectType": 1
        },
        {
            "ActionKey": 3,
            "ActionState": true,
            "CurrentTimeMS": 116002,
            "LoopCounter": 6928,
            "ObjectType": 1
        },
        {
            "ActionKey": 6,
            "ActionState": false,
            "CurrentTimeMS": 116019,
            "LoopCounter": 6929,
            "ObjectType": 1
        },
        {
            "ActionKey": 3,
            "ActionState": false,
            "CurrentTimeMS": 116153,
            "LoopCounter": 6937,
            "ObjectType": 1
        },
        {
            "ActionKey": 6,
            "ActionState": true,
            "CurrentTimeMS": 116153,
            "LoopCounter": 6937,
            "ObjectType": 1
        },
        {
            "ActionKey": 2,
            "ActionState": true,
            "CurrentTimeMS": 116636,
            "LoopCounter": 6966,
            "ObjectType": 1
        },
        {
            "ActionKey": 6,
            "ActionState": false,
            "CurrentTimeMS": 116653,
            "LoopCounter": 6967,
            "ObjectType": 1
        },
        {
            "ActionKey": 4,
            "ActionState": true,
            "CurrentTimeMS": 116720,
            "LoopCounter": 6971,
            "ObjectType": 1
        },
        {
            "ActionKey": 4,
            "ActionState": false,
            "CurrentTimeMS": 116820,
            "LoopCounter": 6977,
            "ObjectType": 1
        },
        {
            "ActionKey": 5,
            "ActionState": true,
            "CurrentTimeMS": 116837,
            "LoopCounter": 6978,
            "ObjectType": 1
        },
        {
            "ActionKey": 2,
            "ActionState": false,
            "CurrentTimeMS": 116870,
            "LoopCounter": 6980,
            "ObjectType": 1
        },
        {
            "ActionKey": 3,
            "ActionState": true,
            "CurrentTimeMS": 117070,
            "LoopCounter": 6992,
            "ObjectType": 1
        },
        {
            "ActionKey": 5,
            "ActionState": false,
            "CurrentTimeMS": 117103,
            "LoopCounter": 6994,
            "ObjectType": 1
        },
        {
            "ActionKey": 3,
            "ActionState": false,
            "CurrentTimeMS": 117387,
            "LoopCounter": 7011,
            "ObjectType": 1
        },
        {
            "ActionKey": 6,
            "ActionState": true,
            "CurrentTimeMS": 117520,
            "LoopCounter": 7019,
            "ObjectType": 1
        },
        {
            "ActionKey": 6,
            "ActionState": false,
            "CurrentTimeMS": 117837,
            "LoopCounter": 7038,
            "ObjectType": 1
        },
        {
            "ActionKey": 4,
            "ActionState": true,
            "CurrentTimeMS": 117854,
            "LoopCounter": 7039,
            "ObjectType": 1
        },
        {
            "ActionKey": 6,
            "ActionState": true,
            "CurrentTimeMS": 118422,
            "LoopCounter": 7073,
            "ObjectType": 1
        },
        {
            "ActionKey": 4,
            "ActionState": false,
            "CurrentTimeMS": 118488,
            "LoopCounter": 7077,
            "ObjectType": 1
        },
        {
            "ActionKey": 4,
            "ActionState": true,
            "CurrentTimeMS": 119907,
            "LoopCounter": 7162,
            "ObjectType": 1
        },
        {
            "ActionKey": 6,
            "ActionState": false,
            "CurrentTimeMS": 120023,
            "LoopCounter": 7169,
            "ObjectType": 1
        },
        {
            "ActionKey": 6,
            "ActionState": true,
            "CurrentTimeMS": 120857,
            "LoopCounter": 7219,
            "ObjectType": 1
        },
        {
            "ActionKey": 4,
            "ActionState": false,
            "CurrentTimeMS": 120957,
            "LoopCounter": 7225,
            "ObjectType": 1
        },
        {
            "ActionKey": 3,
            "ActionState": true,
            "CurrentTimeMS": 124394,
            "LoopCounter": 7431,
            "ObjectType": 1
        },
        {
            "ActionKey": 6,
            "ActionState": false,
            "CurrentTimeMS": 124461,
            "LoopCounter": 7435,
            "ObjectType": 1
        },
        {
            "ActionKey": 5,
            "ActionState": true,
            "CurrentTimeMS": 125328,
            "LoopCounter": 7487,
            "ObjectType": 1
        },
        {
            "ActionKey": 3,
            "ActionState": false,
            "CurrentTimeMS": 125395,
            "LoopCounter": 7491,
            "ObjectType": 1
        },
        {
            "ActionKey": 3,
            "ActionState": true,
            "CurrentTimeMS": 125829,
            "LoopCounter": 7517,
            "ObjectType": 1
        },
        {
            "ActionKey": 5,
            "ActionState": false,
            "CurrentTimeMS": 125846,
            "LoopCounter": 7518,
            "ObjectType": 1
        },
        {
            "ActionKey": 3,
            "ActionState": false,
            "CurrentTimeMS": 126613,
            "LoopCounter": 7564,
            "ObjectType": 1
        },
        {
            "ActionKey": 5,
            "ActionState": true,
            "CurrentTimeMS": 126646,
            "LoopCounter": 7566,
            "ObjectType": 1
        },
        {
            "ActionKey": 5,
            "ActionState": false,
            "CurrentTimeMS": 128782,
            "LoopCounter": 7694,
            "ObjectType": 1
        },
        {
            "ActionKey": 4,
            "ActionState": true,
            "CurrentTimeMS": 129333,
            "LoopCounter": 7727,
            "ObjectType": 1
        },
        {
            "ActionKey": 6,
            "ActionState": true,
            "CurrentTimeMS": 130100,
            "LoopCounter": 7773,
            "ObjectType": 1
        },
        {
            "ActionKey": 4,
            "ActionState": false,
            "CurrentTimeMS": 130216,
            "LoopCounter": 7780,
            "ObjectType": 1
        },
        {
            "ActionKey": 6,
            "ActionState": false,
            "CurrentTimeMS": 130617,
            "LoopCounter": 7804,
            "ObjectType": 1
        },
        {
            "ActionKey": 6,
            "ActionState": true,
            "CurrentTimeMS": 133086,
            "LoopCounter": 7952,
            "ObjectType": 1
        },
        {
            "ActionKey": 6,
            "ActionState": false,
            "CurrentTimeMS": 134554,
            "LoopCounter": 8040,
            "ObjectType": 1
        },
        {
            "ActionKey": 3,
            "ActionState": true,
            "CurrentTimeMS": 135122,
            "LoopCounter": 8074,
            "ObjectType": 1
        },
        {
            "ActionKey": 3,
            "ActionState": false,
            "CurrentTimeMS": 135288,
            "LoopCounter": 8084,
            "ObjectType": 1
        },
        {
            "ActionKey": 5,
            "ActionState": true,
            "CurrentTimeMS": 135889,
            "LoopCounter": 8120,
            "ObjectType": 1
        },
        {
            "ActionKey": 5,
            "ActionState": false,
            "CurrentTimeMS": 136956,
            "LoopCounter": 8184,
            "ObjectType": 1
        },
        {
            "ActionKey": 2,
            "ActionState": true,
            "CurrentTimeMS": 140577,
            "LoopCounter": 8401,
            "ObjectType": 1
        },
        {
            "ActionKey": 5,
            "ActionState": true,
            "CurrentTimeMS": 140627,
            "LoopCounter": 8404,
            "ObjectType": 1
        },
        {
            "ActionKey": 5,
            "ActionState": false,
            "CurrentTimeMS": 140760,
            "LoopCounter": 8412,
            "ObjectType": 1
        },
        {
            "ActionKey": 2,
            "ActionState": false,
            "CurrentTimeMS": 140794,
            "LoopCounter": 8414,
            "ObjectType": 1
        },
        {
            "ActionKey": 6,
            "ActionState": true,
            "CurrentTimeMS": 140827,
            "LoopCounter": 8416,
            "ObjectType": 1
        },
        {
            "ActionKey": 6,
            "ActionState": false,
            "CurrentTimeMS": 141895,
            "LoopCounter": 8480,
            "ObjectType": 1
        },
        {
            "ActionKey": 3,
            "ActionState": true,
            "CurrentTimeMS": 141912,
            "LoopCounter": 8481,
            "ObjectType": 1
        },
        {
            "ActionKey": 3,
            "ActionState": false,
            "CurrentTimeMS": 142112,
            "LoopCounter": 8493,
            "ObjectType": 1
        },
        {
            "ActionKey": 6,
            "ActionState": true,
            "CurrentTimeMS": 142145,
            "LoopCounter": 8495,
            "ObjectType": 1
        },
        {
            "ActionKey": 6,
            "ActionState": false,
            "CurrentTimeMS": 142245,
            "LoopCounter": 8501,
            "ObjectType": 1
        },
        {
            "ActionKey": 6,
            "ActionState": true,
            "CurrentTimeMS": 142312,
            "LoopCounter": 8505,
            "ObjectType": 1
        },
        {
            "ActionKey": 4,
            "ActionState": true,
            "CurrentTimeMS": 142712,
            "LoopCounter": 8529,
            "ObjectType": 1
        },
        {
            "ActionKey": 6,
            "ActionState": false,
            "CurrentTimeMS": 142729,
            "LoopCounter": 8530,
            "ObjectType": 1
        },
        {
            "ActionKey": 6,
            "ActionState": true,
            "CurrentTimeMS": 143113,
            "LoopCounter": 8553,
            "ObjectType": 1
        },
        {
            "ActionKey": 4,
            "ActionState": false,
            "CurrentTimeMS": 143179,
            "LoopCounter": 8557,
            "ObjectType": 1
        },
        {
            "ActionKey": 4,
            "ActionState": true,
            "CurrentTimeMS": 144481,
            "LoopCounter": 8635,
            "ObjectType": 1
        },
        {
            "ActionKey": 6,
            "ActionState": false,
            "CurrentTimeMS": 144514,
            "LoopCounter": 8637,
            "ObjectType": 1
        },
        {
            "ActionKey": 5,
            "ActionState": true,
            "CurrentTimeMS": 145982,
            "LoopCounter": 8725,
            "ObjectType": 1
        },
        {
            "ActionKey": 4,
            "ActionState": false,
            "CurrentTimeMS": 145999,
            "LoopCounter": 8726,
            "ObjectType": 1
        },
        {
            "ActionKey": 5,
            "ActionState": false,
            "CurrentTimeMS": 146132,
            "LoopCounter": 8734,
            "ObjectType": 1
        },
        {
            "ActionKey": 2,
            "ActionState": true,
            "CurrentTimeMS": 146149,
            "LoopCounter": 8735,
            "ObjectType": 1
        },
        {
            "ActionKey": 4,
            "ActionState": true,
            "CurrentTimeMS": 146300,
            "LoopCounter": 8744,
            "ObjectType": 1
        },
        {
            "ActionKey": 4,
            "ActionState": false,
            "CurrentTimeMS": 146382,
            "LoopCounter": 8749,
            "ObjectType": 1
        },
        {
            "ActionKey": 2,
            "ActionState": false,
            "CurrentTimeMS": 146449,
            "LoopCounter": 8753,
            "ObjectType": 1
        },
        {
            "ActionKey": 3,
            "ActionState": true,
            "CurrentTimeMS": 146533,
            "LoopCounter": 8758,
            "ObjectType": 1
        },
        {
            "ActionKey": 3,
            "ActionState": false,
            "CurrentTimeMS": 146666,
            "LoopCounter": 8766,
            "ObjectType": 1
        },
        {
            "ActionKey": 4,
            "ActionState": true,
            "CurrentTimeMS": 147450,
            "LoopCounter": 8813,
            "ObjectType": 1
        },
        {
            "ActionKey": 5,
            "ActionState": true,
            "CurrentTimeMS": 147601,
            "LoopCounter": 8822,
            "ObjectType": 1
        },
        {
            "ActionKey": 4,
            "ActionState": false,
            "CurrentTimeMS": 147618,
            "LoopCounter": 8823,
            "ObjectType": 1
        },
        {
            "ActionKey": 5,
            "ActionState": false,
            "CurrentTimeMS": 147817,
            "LoopCounter": 8835,
            "ObjectType": 1
        },
        {
            "ActionKey": 3,
            "ActionState": true,
            "CurrentTimeMS": 147935,
            "LoopCounter": 8842,
            "ObjectType": 1
        },
        {
            "ActionKey": 3,
            "ActionState": false,
            "CurrentTimeMS": 148101,
            "LoopCounter": 8852,
            "ObjectType": 1
        },
        {
            "ActionKey": 5,
            "ActionState": true,
            "CurrentTimeMS": 148118,
            "LoopCounter": 8853,
            "ObjectType": 1
        },
        {
            "ActionKey": 4,
            "ActionState": true,
            "CurrentTimeMS": 148468,
            "LoopCounter": 8874,
            "ObjectType": 1
        },
        {
            "ActionKey": 5,
            "ActionState": false,
            "CurrentTimeMS": 148535,
            "LoopCounter": 8878,
            "ObjectType": 1
        },
        {
            "ActionKey": 4,
            "ActionState": false,
            "CurrentTimeMS": 148735,
            "LoopCounter": 8890,
            "ObjectType": 1
        },
        {
            "ActionKey": 2,
            "ActionState": true,
            "CurrentTimeMS": 148818,
            "LoopCounter": 8895,
            "ObjectType": 1
        },
        {
            "ActionKey": 4,
            "ActionState": true,
            "CurrentTimeMS": 148902,
            "LoopCounter": 8900,
            "ObjectType": 1
        },
        {
            "ActionKey": 4,
            "ActionState": false,
            "CurrentTimeMS": 148969,
            "LoopCounter": 8904,
            "ObjectType": 1
        },
        {
            "ActionKey": 2,
            "ActionState": false,
            "CurrentTimeMS": 149036,
            "LoopCounter": 8908,
            "ObjectType": 1
        },
        {
            "ActionKey": 3,
            "ActionState": true,
            "CurrentTimeMS": 149086,
            "LoopCounter": 8911,
            "ObjectType": 1
        },
        {
            "ActionKey": 5,
            "ActionState": true,
            "CurrentTimeMS": 149736,
            "LoopCounter": 8950,
            "ObjectType": 1
        },
        {
            "ActionKey": 3,
            "ActionState": false,
            "CurrentTimeMS": 149769,
            "LoopCounter": 8952,
            "ObjectType": 1
        },
        {
            "ActionKey": 4,
            "ActionState": true,
            "CurrentTimeMS": 150137,
            "LoopCounter": 8974,
            "ObjectType": 1
        },
        {
            "ActionKey": 5,
            "ActionState": false,
            "CurrentTimeMS": 150153,
            "LoopCounter": 8975,
            "ObjectType": 1
        },
        {
            "ActionKey": 4,
            "ActionState": false,
            "CurrentTimeMS": 150603,
            "LoopCounter": 9002,
            "ObjectType": 1
        },
        {
            "ActionKey": 3,
            "ActionState": true,
            "CurrentTimeMS": 150721,
            "LoopCounter": 9009,
            "ObjectType": 1
        },
        {
            "ActionKey": 3,
            "ActionState": false,
            "CurrentTimeMS": 150837,
            "LoopCounter": 9016,
            "ObjectType": 1
        },
        {
            "ActionKey": 5,
            "ActionState": true,
            "CurrentTimeMS": 150837,
            "LoopCounter": 9016,
            "ObjectType": 1
        },
        {
            "ActionKey": 4,
            "ActionState": true,
            "CurrentTimeMS": 151588,
            "LoopCounter": 9061,
            "ObjectType": 1
        },
        {
            "ActionKey": 5,
            "ActionState": false,
            "CurrentTimeMS": 151638,
            "LoopCounter": 9064,
            "ObjectType": 1
        },
        {
            "ActionKey": 4,
            "ActionState": false,
            "CurrentTimeMS": 151838,
            "LoopCounter": 9076,
            "ObjectType": 1
        },
        {
            "ActionKey": 2,
            "ActionState": true,
            "CurrentTimeMS": 151872,
            "LoopCounter": 9078,
            "ObjectType": 1
        },
        {
            "ActionKey": 4,
            "ActionState": true,
            "CurrentTimeMS": 151972,
            "LoopCounter": 9084,
            "ObjectType": 1
        },
        {
            "ActionKey": 4,
            "ActionState": false,
            "CurrentTimeMS": 152055,
            "LoopCounter": 9089,
            "ObjectType": 1
        },
        {
            "ActionKey": 5,
            "ActionState": true,
            "CurrentTimeMS": 152072,
            "LoopCounter": 9090,
            "ObjectType": 1
        },
        {
            "ActionKey": 2,
            "ActionState": false,
            "CurrentTimeMS": 152088,
            "LoopCounter": 9091,
            "ObjectType": 1
        },
        {
            "ActionKey": 3,
            "ActionState": true,
            "CurrentTimeMS": 158462,
            "LoopCounter": 9473,
            "ObjectType": 1
        },
        {
            "ActionKey": 5,
            "ActionState": false,
            "CurrentTimeMS": 158462,
            "LoopCounter": 9473,
            "ObjectType": 1
        },
        {
            "ActionKey": 3,
            "ActionState": false,
            "CurrentTimeMS": 158678,
            "LoopCounter": 9486,
            "ObjectType": 1
        },
        {
            "ActionKey": 5,
            "ActionState": true,
            "CurrentTimeMS": 158678,
            "LoopCounter": 9486,
            "ObjectType": 1
        },
        {
            "ActionKey": 4,
            "ActionState": true,
            "CurrentTimeMS": 159196,
            "LoopCounter": 9517,
            "ObjectType": 1
        },
        {
            "ActionKey": 5,
            "ActionState": false,
            "CurrentTimeMS": 159212,
            "LoopCounter": 9518,
            "ObjectType": 1
        },
        {
            "ActionKey": 4,
            "ActionState": false,
            "CurrentTimeMS": 159579,
            "LoopCounter": 9540,
            "ObjectType": 1
        },
        {
            "ActionKey": 6,
            "ActionState": true,
            "CurrentTimeMS": 159746,
            "LoopCounter": 9550,
            "ObjectType": 1
        },
        {
            "ActionKey": 6,
            "ActionState": false,
            "CurrentTimeMS": 160563,
            "LoopCounter": 9599,
            "ObjectType": 1
        },
        {
            "ActionKey": 5,
            "ActionState": true,
            "CurrentTimeMS": 160630,
            "LoopCounter": 9603,
            "ObjectType": 1
        },
        {
            "ActionKey": 4,
            "ActionState": true,
            "CurrentTimeMS": 161698,
            "LoopCounter": 9667,
            "ObjectType": 1
        },
        {
            "ActionKey": 5,
            "ActionState": false,
            "CurrentTimeMS": 161764,
            "LoopCounter": 9671,
            "ObjectType": 1
        },
        {
            "ActionKey": 4,
            "ActionState": false,
            "CurrentTimeMS": 162015,
            "LoopCounter": 9686,
            "ObjectType": 1
        },
        {
            "ActionKey": 2,
            "ActionState": true,
            "CurrentTimeMS": 162065,
            "LoopCounter": 9689,
            "ObjectType": 1
        },
        {
            "ActionKey": 4,
            "ActionState": true,
            "CurrentTimeMS": 162148,
            "LoopCounter": 9694,
            "ObjectType": 1
        },
        {
            "ActionKey": 4,
            "ActionState": false,
            "CurrentTimeMS": 162218,
            "LoopCounter": 9698,
            "ObjectType": 1
        },
        {
            "ActionKey": 2,
            "ActionState": false,
            "CurrentTimeMS": 162265,
            "LoopCounter": 9701,
            "ObjectType": 1
        },
        {
            "ActionKey": 6,
            "ActionState": true,
            "CurrentTimeMS": 162299,
            "LoopCounter": 9703,
            "ObjectType": 1
        },
        {
            "ActionKey": 2,
            "ActionState": true,
            "CurrentTimeMS": 162699,
            "LoopCounter": 9727,
            "ObjectType": 1
        },
        {
            "ActionKey": 6,
            "ActionState": false,
            "CurrentTimeMS": 162716,
            "LoopCounter": 9728,
            "ObjectType": 1
        },
        {
            "ActionKey": 4,
            "ActionState": true,
            "CurrentTimeMS": 162749,
            "LoopCounter": 9730,
            "ObjectType": 1
        },
        {
            "ActionKey": 4,
            "ActionState": false,
            "CurrentTimeMS": 162816,
            "LoopCounter": 9734,
            "ObjectType": 1
        },
        {
            "ActionKey": 2,
            "ActionState": false,
            "CurrentTimeMS": 162883,
            "LoopCounter": 9738,
            "ObjectType": 1
        },
        {
            "ActionKey": 3,
            "ActionState": true,
            "CurrentTimeMS": 162932,
            "LoopCounter": 9741,
            "ObjectType": 1
        },
        {
            "ActionKey": 6,
            "ActionState": true,
            "CurrentTimeMS": 163083,
            "LoopCounter": 9750,
            "ObjectType": 1
        },
        {
            "ActionKey": 3,
            "ActionState": false,
            "CurrentTimeMS": 163099,
            "LoopCounter": 9751,
            "ObjectType": 1
        },
        {
            "ActionKey": 4,
            "ActionState": true,
            "CurrentTimeMS": 163434,
            "LoopCounter": 9771,
            "ObjectType": 1
        },
        {
            "ActionKey": 6,
            "ActionState": false,
            "CurrentTimeMS": 163434,
            "LoopCounter": 9771,
            "ObjectType": 1
        },
        {
            "ActionKey": 4,
            "ActionState": false,
            "CurrentTimeMS": 163683,
            "LoopCounter": 9786,
            "ObjectType": 1
        },
        {
            "ActionKey": 2,
            "ActionState": true,
            "CurrentTimeMS": 163801,
            "LoopCounter": 9793,
            "ObjectType": 1
        },
        {
            "ActionKey": 4,
            "ActionState": true,
            "CurrentTimeMS": 163900,
            "LoopCounter": 9799,
            "ObjectType": 1
        },
        {
            "ActionKey": 4,
            "ActionState": false,
            "CurrentTimeMS": 163984,
            "LoopCounter": 9804,
            "ObjectType": 1
        },
        {
            "ActionKey": 2,
            "ActionState": false,
            "CurrentTimeMS": 164034,
            "LoopCounter": 9807,
            "ObjectType": 1
        },
        {
            "ActionKey": 6,
            "ActionState": true,
            "CurrentTimeMS": 164050,
            "LoopCounter": 9808,
            "ObjectType": 1
        },
        {
            "ActionKey": 4,
            "ActionState": true,
            "CurrentTimeMS": 164367,
            "LoopCounter": 9827,
            "ObjectType": 1
        },
        {
            "ActionKey": 6,
            "ActionState": false,
            "CurrentTimeMS": 164434,
            "LoopCounter": 9831,
            "ObjectType": 1
        },
        {
            "ActionKey": 6,
            "ActionState": true,
            "CurrentTimeMS": 164668,
            "LoopCounter": 9845,
            "ObjectType": 1
        },
        {
            "ActionKey": 4,
            "ActionState": false,
            "CurrentTimeMS": 164701,
            "LoopCounter": 9847,
            "ObjectType": 1
        },
        {
            "ActionKey": 3,
            "ActionState": true,
            "CurrentTimeMS": 164885,
            "LoopCounter": 9858,
            "ObjectType": 1
        },
        {
            "ActionKey": 6,
            "ActionState": false,
            "CurrentTimeMS": 164885,
            "LoopCounter": 9858,
            "ObjectType": 1
        },
        {
            "ActionKey": 5,
            "ActionState": true,
            "CurrentTimeMS": 165635,
            "LoopCounter": 9903,
            "ObjectType": 1
        },
        {
            "ActionKey": 3,
            "ActionState": false,
            "CurrentTimeMS": 165669,
            "LoopCounter": 9905,
            "ObjectType": 1
        },
        {
            "ActionKey": 3,
            "ActionState": true,
            "CurrentTimeMS": 166303,
            "LoopCounter": 9943,
            "ObjectType": 1
        },
        {
            "ActionKey": 5,
            "ActionState": false,
            "CurrentTimeMS": 166336,
            "LoopCounter": 9945,
            "ObjectType": 1
        },
        {
            "ActionKey": 5,
            "ActionState": true,
            "CurrentTimeMS": 167337,
            "LoopCounter": 10005,
            "ObjectType": 1
        },
        {
            "ActionKey": 3,
            "ActionState": false,
            "CurrentTimeMS": 167453,
            "LoopCounter": 10012,
            "ObjectType": 1
        },
        {
            "ActionKey": 2,
            "ActionState": true,
            "CurrentTimeMS": 168855,
            "LoopCounter": 10096,
            "ObjectType": 1
        },
        {
            "ActionKey": 5,
            "ActionState": false,
            "CurrentTimeMS": 168855,
            "LoopCounter": 10096,
            "ObjectType": 1
        },
        {
            "ActionKey": 5,
            "ActionState": true,
            "CurrentTimeMS": 169005,
            "LoopCounter": 10105,
            "ObjectType": 1
        },
        {
            "ActionKey": 5,
            "ActionState": false,
            "CurrentTimeMS": 170290,
            "LoopCounter": 10182,
            "ObjectType": 1
        },
        {
            "ActionKey": 2,
            "ActionState": false,
            "CurrentTimeMS": 170323,
            "LoopCounter": 10184,
            "ObjectType": 1
        },
        {
            "ActionKey": 3,
            "ActionState": true,
            "CurrentTimeMS": 170574,
            "LoopCounter": 10199,
            "ObjectType": 1
        },
        {
            "ActionKey": 3,
            "ActionState": false,
            "CurrentTimeMS": 170723,
            "LoopCounter": 10208,
            "ObjectType": 1
        },
        {
            "ActionKey": 2,
            "ActionState": true,
            "CurrentTimeMS": 170990,
            "LoopCounter": 10224,
            "ObjectType": 1
        },
        {
            "ActionKey": 5,
            "ActionState": true,
            "CurrentTimeMS": 171057,
            "LoopCounter": 10228,
            "ObjectType": 1
        },
        {
            "ActionKey": 5,
            "ActionState": false,
            "CurrentTimeMS": 171157,
            "LoopCounter": 10234,
            "ObjectType": 1
        },
        {
            "ActionKey": 2,
            "ActionState": false,
            "CurrentTimeMS": 171241,
            "LoopCounter": 10239,
            "ObjectType": 1
        },
        {
            "ActionKey": 6,
            "ActionState": true,
            "CurrentTimeMS": 171474,
            "LoopCounter": 10253,
            "ObjectType": 1
        },
        {
            "ActionKey": 6,
            "ActionState": false,
            "CurrentTimeMS": 171607,
            "LoopCounter": 10261,
            "ObjectType": 1
        },
        {
            "ActionKey": 5,
            "ActionState": true,
            "CurrentTimeMS": 172475,
            "LoopCounter": 10313,
            "ObjectType": 1
        },
        {
            "ActionKey": 3,
            "ActionState": true,
            "CurrentTimeMS": 172976,
            "LoopCounter": 10343,
            "ObjectType": 1
        },
        {
            "ActionKey": 5,
            "ActionState": false,
            "CurrentTimeMS": 173026,
            "LoopCounter": 10346,
            "ObjectType": 1
        },
        {
            "ActionKey": 3,
            "ActionState": false,
            "CurrentTimeMS": 173126,
            "LoopCounter": 10352,
            "ObjectType": 1
        },
        {
            "ActionKey": 5,
            "ActionState": true,
            "CurrentTimeMS": 173126,
            "LoopCounter": 10352,
            "ObjectType": 1
        },
        {
            "ActionKey": 5,
            "ActionState": false,
            "CurrentTimeMS": 173393,
            "LoopCounter": 10368,
            "ObjectType": 1
        },
        {
            "ActionKey": 2,
            "ActionState": true,
            "CurrentTimeMS": 173443,
            "LoopCounter": 10371,
            "ObjectType": 1
        },
        {
            "ActionKey": 5,
            "ActionState": true,
            "CurrentTimeMS": 173510,
            "LoopCounter": 10375,
            "ObjectType": 1
        },
        {
            "ActionKey": 5,
            "ActionState": false,
            "CurrentTimeMS": 173610,
            "LoopCounter": 10381,
            "ObjectType": 1
        },
        {
            "ActionKey": 2,
            "ActionState": false,
            "CurrentTimeMS": 173676,
            "LoopCounter": 10385,
            "ObjectType": 1
        },
        {
            "ActionKey": 3,
            "ActionState": true,
            "CurrentTimeMS": 173743,
            "LoopCounter": 10389,
            "ObjectType": 1
        },
        {
            "ActionKey": 3,
            "ActionState": false,
            "CurrentTimeMS": 173877,
            "LoopCounter": 10397,
            "ObjectType": 1
        },
        {
            "ActionKey": 5,
            "ActionState": true,
            "CurrentTimeMS": 174394,
            "LoopCounter": 10428,
            "ObjectType": 1
        },
        {
            "ActionKey": 5,
            "ActionState": false,
            "CurrentTimeMS": 174528,
            "LoopCounter": 10436,
            "ObjectType": 1
        },
        {
            "ActionKey": 2,
            "ActionState": true,
            "CurrentTimeMS": 174577,
            "LoopCounter": 10439,
            "ObjectType": 1
        },
        {
            "ActionKey": 5,
            "ActionState": true,
            "CurrentTimeMS": 174644,
            "LoopCounter": 10443,
            "ObjectType": 1
        },
        {
            "ActionKey": 5,
            "ActionState": false,
            "CurrentTimeMS": 174745,
            "LoopCounter": 10449,
            "ObjectType": 1
        },
        {
            "ActionKey": 2,
            "ActionState": false,
            "CurrentTimeMS": 174811,
            "LoopCounter": 10453,
            "ObjectType": 1
        },
        {
            "ActionKey": 3,
            "ActionState": true,
            "CurrentTimeMS": 174912,
            "LoopCounter": 10459,
            "ObjectType": 1
        },
        {
            "ActionKey": 5,
            "ActionState": true,
            "CurrentTimeMS": 174995,
            "LoopCounter": 10464,
            "ObjectType": 1
        },
        {
            "ActionKey": 3,
            "ActionState": false,
            "CurrentTimeMS": 175044,
            "LoopCounter": 10467,
            "ObjectType": 1
        },
        {
            "ActionKey": 4,
            "ActionState": true,
            "CurrentTimeMS": 175712,
            "LoopCounter": 10507,
            "ObjectType": 1
        },
        {
            "ActionKey": 5,
            "ActionState": false,
            "CurrentTimeMS": 175745,
            "LoopCounter": 10509,
            "ObjectType": 1
        },
        {
            "ActionKey": 4,
            "ActionState": false,
            "CurrentTimeMS": 175962,
            "LoopCounter": 10522,
            "ObjectType": 1
        },
        {
            "ActionKey": 6,
            "ActionState": true,
            "CurrentTimeMS": 176063,
            "LoopCounter": 10528,
            "ObjectType": 1
        },
        {
            "ActionKey": 6,
            "ActionState": false,
            "CurrentTimeMS": 176896,
            "LoopCounter": 10578,
            "ObjectType": 1
        },
        {
            "ActionKey": 5,
            "ActionState": true,
            "CurrentTimeMS": 176930,
            "LoopCounter": 10580,
            "ObjectType": 1
        },
        {
            "ActionKey": 4,
            "ActionState": true,
            "CurrentTimeMS": 177647,
            "LoopCounter": 10623,
            "ObjectType": 1
        },
        {
            "ActionKey": 5,
            "ActionState": false,
            "CurrentTimeMS": 177714,
            "LoopCounter": 10627,
            "ObjectType": 1
        },
        {
            "ActionKey": 4,
            "ActionState": false,
            "CurrentTimeMS": 177915,
            "LoopCounter": 10639,
            "ObjectType": 1
        },
        {
            "ActionKey": 6,
            "ActionState": true,
            "CurrentTimeMS": 177931,
            "LoopCounter": 10640,
            "ObjectType": 1
        },
        {
            "ActionKey": 6,
            "ActionState": false,
            "CurrentTimeMS": 178482,
            "LoopCounter": 10673,
            "ObjectType": 1
        },
        {
            "ActionKey": 5,
            "ActionState": true,
            "CurrentTimeMS": 178515,
            "LoopCounter": 10675,
            "ObjectType": 1
        },
        {
            "ActionKey": 4,
            "ActionState": true,
            "CurrentTimeMS": 178982,
            "LoopCounter": 10703,
            "ObjectType": 1
        },
        {
            "ActionKey": 5,
            "ActionState": false,
            "CurrentTimeMS": 179032,
            "LoopCounter": 10706,
            "ObjectType": 1
        },
        {
            "ActionKey": 6,
            "ActionState": true,
            "CurrentTimeMS": 179299,
            "LoopCounter": 10722,
            "ObjectType": 1
        },
        {
            "ActionKey": 4,
            "ActionState": false,
            "CurrentTimeMS": 179316,
            "LoopCounter": 10723,
            "ObjectType": 1
        },
        {
            "ActionKey": 6,
            "ActionState": false,
            "CurrentTimeMS": 179716,
            "LoopCounter": 10747,
            "ObjectType": 1
        },
        {
            "ActionKey": 2,
            "ActionState": true,
            "CurrentTimeMS": 179783,
            "LoopCounter": 10751,
            "ObjectType": 1
        },
        {
            "ActionKey": 6,
            "ActionState": true,
            "CurrentTimeMS": 179933,
            "LoopCounter": 10760,
            "ObjectType": 1
        },
        {
            "ActionKey": 6,
            "ActionState": false,
            "CurrentTimeMS": 180016,
            "LoopCounter": 10765,
            "ObjectType": 1
        },
        {
            "ActionKey": 2,
            "ActionState": false,
            "CurrentTimeMS": 180052,
            "LoopCounter": 10767,
            "ObjectType": 1
        },
        {
            "ActionKey": 4,
            "ActionState": true,
            "CurrentTimeMS": 180100,
            "LoopCounter": 10770,
            "ObjectType": 1
        },
        {
            "ActionKey": 6,
            "ActionState": true,
            "CurrentTimeMS": 180700,
            "LoopCounter": 10806,
            "ObjectType": 1
        },
        {
            "ActionKey": 4,
            "ActionState": false,
            "CurrentTimeMS": 180867,
            "LoopCounter": 10816,
            "ObjectType": 1
        },
        {
            "ActionKey": 6,
            "ActionState": false,
            "CurrentTimeMS": 180934,
            "LoopCounter": 10820,
            "ObjectType": 1
        },
        {
            "ActionKey": 2,
            "ActionState": true,
            "CurrentTimeMS": 181068,
            "LoopCounter": 10828,
            "ObjectType": 1
        },
        {
            "ActionKey": 3,
            "ActionState": true,
            "CurrentTimeMS": 181134,
            "LoopCounter": 10832,
            "ObjectType": 1
        },
        {
            "ActionKey": 3,
            "ActionState": false,
            "CurrentTimeMS": 181184,
            "LoopCounter": 10835,
            "ObjectType": 1
        },
        {
            "ActionKey": 2,
            "ActionState": false,
            "CurrentTimeMS": 181217,
            "LoopCounter": 10837,
            "ObjectType": 1
        },
        {
            "ActionKey": 6,
            "ActionState": true,
            "CurrentTimeMS": 181251,
            "LoopCounter": 10839,
            "ObjectType": 1
        },
        {
            "ActionKey": 6,
            "ActionState": false,
            "CurrentTimeMS": 181384,
            "LoopCounter": 10847,
            "ObjectType": 1
        },
        {
            "ActionKey": 2,
            "ActionState": true,
            "CurrentTimeMS": 181451,
            "LoopCounter": 10851,
            "ObjectType": 1
        },
        {
            "ActionKey": 3,
            "ActionState": true,
            "CurrentTimeMS": 181551,
            "LoopCounter": 10857,
            "ObjectType": 1
        },
        {
            "ActionKey": 3,
            "ActionState": false,
            "CurrentTimeMS": 181601,
            "LoopCounter": 10860,
            "ObjectType": 1
        },
        {
            "ActionKey": 2,
            "ActionState": false,
            "CurrentTimeMS": 181618,
            "LoopCounter": 10861,
            "ObjectType": 1
        },
        {
            "ActionKey": 6,
            "ActionState": true,
            "CurrentTimeMS": 181684,
            "LoopCounter": 10865,
            "ObjectType": 1
        },
        {
            "ActionKey": 6,
            "ActionState": false,
            "CurrentTimeMS": 181818,
            "LoopCounter": 10873,
            "ObjectType": 1
        },
        {
            "ActionKey": 2,
            "ActionState": true,
            "CurrentTimeMS": 181868,
            "LoopCounter": 10876,
            "ObjectType": 1
        },
        {
            "ActionKey": 3,
            "ActionState": true,
            "CurrentTimeMS": 181934,
            "LoopCounter": 10880,
            "ObjectType": 1
        },
        {
            "ActionKey": 3,
            "ActionState": false,
            "CurrentTimeMS": 182001,
            "LoopCounter": 10884,
            "ObjectType": 1
        },
        {
            "ActionKey": 2,
            "ActionState": false,
            "CurrentTimeMS": 182035,
            "LoopCounter": 10886,
            "ObjectType": 1
        },
        {
            "ActionKey": 6,
            "ActionState": true,
            "CurrentTimeMS": 182068,
            "LoopCounter": 10888,
            "ObjectType": 1
        },
        {
            "ActionKey": 6,
            "ActionState": false,
            "CurrentTimeMS": 182853,
            "LoopCounter": 10935,
            "ObjectType": 1
        },
        {
            "ActionKey": 2,
            "ActionState": true,
            "CurrentTimeMS": 182953,
            "LoopCounter": 10941,
            "ObjectType": 1
        },
        {
            "ActionKey": 6,
            "ActionState": true,
            "CurrentTimeMS": 183069,
            "LoopCounter": 10948,
            "ObjectType": 1
        },
        {
            "ActionKey": 6,
            "ActionState": false,
            "CurrentTimeMS": 183169,
            "LoopCounter": 10954,
            "ObjectType": 1
        },
        {
            "ActionKey": 2,
            "ActionState": false,
            "CurrentTimeMS": 183237,
            "LoopCounter": 10958,
            "ObjectType": 1
        },
        {
            "ActionKey": 3,
            "ActionState": true,
            "CurrentTimeMS": 183353,
            "LoopCounter": 10965,
            "ObjectType": 1
        },
        {
            "ActionKey": 5,
            "ActionState": true,
            "CurrentTimeMS": 184638,
            "LoopCounter": 11042,
            "ObjectType": 1
        },
        {
            "ActionKey": 3,
            "ActionState": false,
            "CurrentTimeMS": 184721,
            "LoopCounter": 11047,
            "ObjectType": 1
        },
        {
            "CurrentTimeMS": 186623,
            "LoopCounter": 11161,
            "ObjectProperties": {
                "victory": true
            },
            "ObjectType": 2,
            "ValidateType": 5
        },
        {
            "CurrentTimeMS": 186623,
            "LoopCounter": 11161,
            "ObjectProperties": null,
            "ObjectType": 2,
            "ValidateType": 4
        }
    ],
    "UserHash": [
        0,
        0,
        0,
        0,
        0,
        0,
        0,
        0,
        0,
        0,
        0,
        0,
        0,
        0,
        0,
        0,
        0,
        0,
        0,
        0,
        0,
        0,
        0,
        0,
        0,
        0,
        0,
        0,
        0,
        0,
        0,
        0,
        0,
        0,
        0,
        0,
        0,
        0,
        0,
        0,
        0,
        0,
        0,
        0,
        0,
        0,
        0,
        0,
        0,
        0,
        0,
        0,
        0,
        0,
        0,
        0,
        0,
        0,
        0,
        0,
        0,
        0,
        0,
        0
    ]
}
